joda_misc/__init__.py
joda_misc/admin.py
joda_misc/apps.py
joda_misc/models.py
joda_misc/router.py
joda_misc/serializers.py
joda_misc/views.py
joda_misc/migrations/0001_initial.py
joda_misc/migrations/0002_default_misc_type.py
joda_misc/migrations/__init__.py
joda_misc/tests/__init__.py
joda_misc/tests/test_init.py
joda_misc-0.1.0a1.dist-info/DESCRIPTION.rst
joda_misc-0.1.0a1.dist-info/METADATA
joda_misc-0.1.0a1.dist-info/RECORD
joda_misc-0.1.0a1.dist-info/WHEEL
joda_misc-0.1.0a1.dist-info/metadata.json
joda_misc-0.1.0a1.dist-info/top_level.txt
